crosslang_wrapper_test/__init__.py
crosslang_wrapper_test-1.0.1.dist-info/METADATA
crosslang_wrapper_test-1.0.1.dist-info/WHEEL
crosslang_wrapper_test-1.0.1.dist-info/top_level.txt
crosslang_wrapper_test-1.0.1.dist-info/RECORD
