Metadata-Version: 2.1
Name: crosslang-wrapper-test
Version: 1.0.1
Summary: Python SDK for Wrapper via REST API
Author: insanely_tamojit
Requires-Dist: requests
